django_fab_deployer/exceptions.py
django_fab_deployer/fabfile.py
django_fab_deployer/runner.py
django_fab_deployer/__init__.py
django_fab_deployer-0.0.11.dist-info/dependency_links.txt
django_fab_deployer-0.0.11.dist-info/DESCRIPTION.rst
django_fab_deployer-0.0.11.dist-info/entry_points.txt
django_fab_deployer-0.0.11.dist-info/METADATA
django_fab_deployer-0.0.11.dist-info/metadata.json
django_fab_deployer-0.0.11.dist-info/RECORD
django_fab_deployer-0.0.11.dist-info/top_level.txt
django_fab_deployer-0.0.11.dist-info/WHEEL
