Metadata-Version: 2.0
Name: django-fab-deployer
Version: 0.0.11
Summary: TODO Add description
Home-page: https://github.com/illagrenan/django-fab-deployer
Author: Vašek Dohnal
Author-email: vaclav.dohnal@gmail.com
License: MIT
Platform: UNKNOWN
Classifier: Programming Language :: Python :: 2.7
Classifier: License :: OSI Approved :: MIT License
Classifier: Development Status :: 3 - Alpha
Classifier: Environment :: Web Environment
Classifier: Environment :: Console
Classifier: Intended Audience :: Developers
Requires-Dist: fabric
Requires-Dist: color-printer
Requires-Dist: paramiko (==1.15.1)
